Dino/__init__.py
Dino/_main.py
DinoHash-0.7.dist-info/METADATA
DinoHash-0.7.dist-info/WHEEL
DinoHash-0.7.dist-info/top_level.txt
DinoHash-0.7.dist-info/RECORD
